{"_type":"export","__export_format":4,"__export_date":"2020-07-14T03:30:00.244Z","__export_source":"insomnia.desktop.app:v2020.3.0","resources":[{"_id":"req_c31c377d16984be992571e41582a012d","authentication":{},"body":{},"created":1594554893683,"description":"","headers":[],"isPrivate":false,"metaSortKey":-1594554893683,"method":"GET","modified":1594554947036,"name":"showAllItems","parameters":[],"parentId":"fld_502c1ee0a5d94064918c884e89045f2c","settingDisableRenderRequestBody":false,"settingEncodeUrl":true,"settingFollowRedirects":"global","settingRebuildPath":true,"settingSendCookies":true,"settingStoreCookies":true,"url":"{{ baseURL }}/items","_type":"request"},{"_id":"fld_502c1ee0a5d94064918c884e89045f2c","created":1594554870232,"description":"","environment":{},"environmentPropertyOrder":null,"metaSortKey":-1594554870232,"modified":1594554870232,"name":"ItemsController","parentId":"wrk_40b2e58bb8da465f88c8142fc696b163","_type":"request_group"},{"_id":"wrk_40b2e58bb8da465f88c8142fc696b163","created":1593919243704,"description":"","modified":1594567276472,"name":"Ecoleta","parentId":null,"scope":null,"_type":"workspace"},{"_id":"req_7c9d99b2fc91457dad1164d4aa433d51","authentication":{},"body":{},"created":1593981298052,"description":"","headers":[],"isPrivate":false,"metaSortKey":-1593981298052,"method":"GET","modified":1594559798319,"name":"findOnePoint","parameters":[],"parentId":"fld_0cdef4e8af6d464c8aea274852112c19","settingDisableRenderRequestBody":false,"settingEncodeUrl":true,"settingFollowRedirects":"global","settingRebuildPath":true,"settingSendCookies":true,"settingStoreCookies":true,"url":"{{ baseURL  }}/points/3","_type":"request"},{"_id":"fld_0cdef4e8af6d464c8aea274852112c19","created":1593919348014,"description":"","environment":{},"environmentPropertyOrder":null,"metaSortKey":-1593919348014,"modified":1593919348014,"name":"Points","parentId":"wrk_40b2e58bb8da465f88c8142fc696b163","_type":"request_group"},{"_id":"req_87b56142746946099659aa0926e9e73e","authentication":{},"body":{"mimeType":"multipart/form-data","params":[{"id":"pair_b2788f6df60d4ea195af24caa4b478d3","name":"name","value":"mercado do josé"},{"description":"","id":"pair_50393696f1aa4eeeb79dae9e37baa0bd","name":"email","value":"mercado@doze.com.br"},{"description":"","id":"pair_4f6c16a9854542b8b7adfd1c0b3ee579","name":"whatsapp","value":"980000000"},{"description":"","id":"pair_d1b8ef9c89164989919a1df3ce2490fd","name":"latitude","value":"-22.9988425,"},{"description":"","id":"pair_8ebbd79b93394422a52b9d246a0942b9","name":"longitude","value":"-43.5510810"},{"description":"","id":"pair_20682c7075c847f6bd6b8fc9f78444c4","name":"city","value":"Rio de Janeiro"},{"description":"","id":"pair_e7316ef140eb4a6190f2f8b334b7ec0d","name":"uf","value":"RJ"},{"description":"","id":"pair_7a53a15f55b74ab695853f7d443ed61b","name":"items","value":"1, 2, 6"},{"description":"","fileName":"/home/admi/Área de Trabalho/market.jpeg","id":"pair_1a75ef9063c14526a33c9d7b7ff8250c","name":"image","type":"file","value":""}]},"created":1593919420105,"description":"","headers":[{"id":"pair_30549780828a400fa5d6b6923370c1b5","name":"Content-Type","value":"multipart/form-data"}],"isPrivate":false,"metaSortKey":-1593919420105,"method":"POST","modified":1594555308039,"name":"createPoint","parameters":[],"parentId":"fld_0cdef4e8af6d464c8aea274852112c19","settingDisableRenderRequestBody":false,"settingEncodeUrl":true,"settingFollowRedirects":"global","settingRebuildPath":true,"settingSendCookies":true,"settingStoreCookies":true,"url":"{{ baseURL  }}/points","_type":"request"},{"_id":"req_d7af6af45ae947fcbcda47b5820b3543","authentication":{},"body":{},"created":1593919353531,"description":"","headers":[],"isPrivate":false,"metaSortKey":-1593919353532,"method":"GET","modified":1593982659916,"name":"filteredPoints","parameters":[{"description":"","id":"pair_c2b070cfc85e4699b39e6073bfcc9cda","name":"city","value":"Rio de Janeiro"},{"description":"","id":"pair_39166cea93bf425086059565128c8613","name":"uf","value":"RJ"},{"description":"","id":"pair_9cfcd9d843614a77b477f0ec3262fb2f","name":"items","value":"1"}],"parentId":"fld_0cdef4e8af6d464c8aea274852112c19","settingDisableRenderRequestBody":false,"settingEncodeUrl":true,"settingFollowRedirects":"global","settingRebuildPath":true,"settingSendCookies":true,"settingStoreCookies":true,"url":"{{ baseURL  }}/points","_type":"request"},{"_id":"env_cda3aa3b3e3a4d4c710228da31cb161679cc181a","color":null,"created":1593919243823,"data":{},"dataPropertyOrder":null,"isPrivate":false,"metaSortKey":1593919243823,"modified":1593919243823,"name":"Base Environment","parentId":"wrk_40b2e58bb8da465f88c8142fc696b163","_type":"environment"},{"_id":"jar_cda3aa3b3e3a4d4c710228da31cb161679cc181a","cookies":[],"created":1593919243827,"modified":1593919243827,"name":"Default Jar","parentId":"wrk_40b2e58bb8da465f88c8142fc696b163","_type":"cookie_jar"},{"_id":"spc_9d9d5060347f4593bf6832fb3e777665","contentType":"yaml","contents":"","created":1593919243708,"fileName":"Insomnia","modified":1593919243708,"parentId":"wrk_40b2e58bb8da465f88c8142fc696b163","_type":"api_spec"},{"_id":"env_e16f77734e624cf98bafca94c1f76e91","color":"#fffe00","created":1593919260647,"data":{"baseURL":"http://localhost:3333"},"dataPropertyOrder":{"&":["baseURL"]},"isPrivate":false,"metaSortKey":1593919260647,"modified":1593919322006,"name":"development","parentId":"env_cda3aa3b3e3a4d4c710228da31cb161679cc181a","_type":"environment"}]}